signalplot/__init__.py
signalplot/axes.py
signalplot/labels.py
signalplot/style.py
signalplot-0.1.2.dist-info/licenses/LICENSE
signalplot-0.1.2.dist-info/METADATA
signalplot-0.1.2.dist-info/WHEEL
signalplot-0.1.2.dist-info/top_level.txt
signalplot-0.1.2.dist-info/RECORD
